{"coord":{"pos":"2_11_8_3","capAbsoluteX":3360,"capAbsoluteY":672,"absoluteWidth":16,"absoluteHeight":16,"subElements":{"planets":[{"pos":"2_11_8_3_1","capAbsoluteX":3372,"capAbsoluteY":680,"absoluteWidth":4,"absoluteHeight":4,"owner":{"cap_id":"830","cap_name":"cdt. Eicho"},"name":"2.11.8.3.1","image":"\/images\/universe\/aride_fg3.jpg"},{"pos":"2_11_8_3_2","capAbsoluteX":3363,"capAbsoluteY":672,"absoluteWidth":4,"absoluteHeight":4,"owner":null,"name":"C&eacute;rul&eacute;en","image":"\/images\/universe\/aride_fg3.jpg"},{"pos":"2_11_8_3_3","capAbsoluteX":3372,"capAbsoluteY":672,"absoluteWidth":4,"absoluteHeight":4,"owner":{"cap_id":"830","cap_name":"cdt. Eicho"},"name":"2.11.8.3.3","image":"\/images\/universe\/desertique_fg3.jpg"},{"pos":"2_11_8_3_4","capAbsoluteX":3360,"capAbsoluteY":677,"absoluteWidth":4,"absoluteHeight":4,"owner":null,"name":"Hooker","image":"\/images\/universe\/aride_fg3.jpg"}],"pc":{"capAbsoluteX":3366,"capAbsoluteY":676,"absoluteWidth":4,"absoluteHeight":4,"image":"\/images\/universe\/coordonnee.jpg"}},"fleets":[{"cap_id":76,"cap_name":"cdte. Aryakis"},{"cap_id":1169,"cap_name":"cdt. Lannes"},{"cap_id":1293,"cap_name":"coa. Ev&egrave;ne"}]},"cap":{"minVisiblePosLevel":1,"absoluteGrid":{"width":32768,"height":32768}}}